faced/load_data.py
faced/classifiers/__init__.py
faced/classifiers/eye_classifier.py
faced/classifiers/face_classifier.py
faced/convert/__init__.py
faced/convert/converters.py
faced/cv_utils/__init__.py
faced/cv_utils/cv_utils.py
faced/data/__init__.py
faced/data/lab.zip
faced/data/mark_1.png
faced/data/test.zip
faced/main/__init__.py
faced/main/faced.py
faced/main/faced_by_keyword.py
faced/pil_utils/__init__.py
faced/pil_utils/pil_utils.py
faced/tests/__init__.py
faced/tests/test_classifiers.py
faced/tests/test_converters.py
faced/tests/test_cvutils.py
faced/tests/test_load_data.py
faced/tests/test_main.py
faced/tests/test_makeinit.py
faced/utils/__init__.py
faced/utils/folder_size.py
faced/utils/make_init.py
faced/utils/ram_stats.py
faced-0.0.8.dist-info/licenses/LICENSE
faced-0.0.8.dist-info/METADATA
faced-0.0.8.dist-info/WHEEL
faced-0.0.8.dist-info/top_level.txt
faced-0.0.8.dist-info/RECORD
