Metadata-Version: 2.4
Name: faced
Version: 0.0.8
Summary: FaceD for Static face detection
Home-page: https://github.com/AlphaPrime7/faced
Author: Tingwei Adeck
Author-email: awesome.tingwei@outlook.com
License: LICENSE
Classifier: Programming Language :: Python :: 3
Classifier: Operating System :: OS Independent
Requires-Python: >=3.12.9
License-File: LICENSE
Requires-Dist: opencv-contrib-python-headless
Requires-Dist: opencv-python-headless
Requires-Dist: opencv-python
Requires-Dist: pytesseract>=0.3.10
Requires-Dist: pillow>=10.3.0
Requires-Dist: matplotlib>=3.9.0
Dynamic: author
Dynamic: author-email
Dynamic: classifier
Dynamic: description
Dynamic: home-page
Dynamic: license
Dynamic: license-file
Dynamic: requires-dist
Dynamic: requires-python
Dynamic: summary
